flask_bootstrapforms/__init__.py
flask_bootstrapforms/app.py
Flask_BootstrapForms-0.1.6.dist-info/LICENSE
Flask_BootstrapForms-0.1.6.dist-info/METADATA
Flask_BootstrapForms-0.1.6.dist-info/WHEEL
Flask_BootstrapForms-0.1.6.dist-info/top_level.txt
Flask_BootstrapForms-0.1.6.dist-info/zip-safe
Flask_BootstrapForms-0.1.6.dist-info/RECORD
