Metadata-Version: 2.1
Name: Flask-BootstrapForms
Version: 0.1.6
Summary: Generator for Bootstrap form elements
Home-page: https://github.com/CheeseCake87/Flask-BootstrapForms
Author: David Carmichael
Author-email: carmichaelits@gmail.com
License: MIT
Platform: any
Classifier: Environment :: Web Environment
Classifier: Intended Audience :: Developers
Classifier: License :: OSI Approved :: MIT License
Classifier: Operating System :: OS Independent
Classifier: Programming Language :: Python
Classifier: Topic :: Internet :: WWW/HTTP :: Dynamic Content
Classifier: Topic :: Software Development :: Libraries :: Python Modules
Requires-Python: >=3.10
License-File: LICENSE
Requires-Dist: Flask
